README.md
setup.py
src/ekster/__init__.py
src/ekster.egg-info/PKG-INFO
src/ekster.egg-info/SOURCES.txt
src/ekster.egg-info/dependency_links.txt
src/ekster.egg-info/requires.txt
src/ekster.egg-info/top_level.txt